readcomb/classification.py
readcomb/false_positives.py
readcomb/filter.py
readcomb-0.4.13.data/scripts/bamprep.py
readcomb-0.4.13.data/scripts/false_positives.py
readcomb-0.4.13.data/scripts/filter.py
readcomb-0.4.13.data/scripts/vcfprep.py
readcomb-0.4.13.dist-info/LICENSE
readcomb-0.4.13.dist-info/METADATA
readcomb-0.4.13.dist-info/WHEEL
readcomb-0.4.13.dist-info/entry_points.txt
readcomb-0.4.13.dist-info/top_level.txt
readcomb-0.4.13.dist-info/RECORD
