Metadata-Version: 2.1
Name: readcomb
Version: 0.4.13
Summary: Fast detection of recombinant reads in BAMs
Home-page: https://github.com/ness-lab/readcomb
License: GNU GPLV3+
Platform: UNKNOWN
Classifier: License :: OSI Approved :: GNU General Public License v3 or later (GPLv3+)
Classifier: Programming Language :: Python :: 3
Classifier: Programming Language :: Python :: 3.5
Classifier: Development Status :: 3 - Alpha
Classifier: Operating System :: OS Independent
License-File: LICENSE
Requires-Dist: cyvcf2
Requires-Dist: pysam
Requires-Dist: pandas
Requires-Dist: tqdm
